query_inspector/__init__.py
query_inspector/admin.py
query_inspector/app_settings.py
query_inspector/apps.py
query_inspector/exporters.py
query_inspector/generic.py
query_inspector/log.py
query_inspector/middleware.py
query_inspector/models.py
query_inspector/query_debugger.py
query_inspector/run_sitecopy.py
query_inspector/sql.py
query_inspector/trace.py
query_inspector/views.py
query_inspector/management/__init__.py
query_inspector/management/__pycache__/__init__.cpython-310.pyc
query_inspector/management/__pycache__/__init__.cpython-38.pyc
query_inspector/management/commands/__init__.py
query_inspector/management/commands/dump_local_data.py
query_inspector/management/commands/load_stock_queries.py
query_inspector/management/commands/restore_from_local_data.py
query_inspector/management/commands/sitecopy.py
query_inspector/management/commands/__pycache__/__init__.cpython-310.pyc
query_inspector/management/commands/__pycache__/__init__.cpython-38.pyc
query_inspector/management/commands/__pycache__/load_stock_queries.cpython-310.pyc
query_inspector/management/commands/__pycache__/load_stock_queries.cpython-38.pyc
query_inspector/management/commands/__pycache__/sitecopy.cpython-38.pyc
query_inspector/migrations/0001_initial.py
query_inspector/migrations/0002_query_default_parameters.py
query_inspector/migrations/0003_alter_query_default_parameters.py
query_inspector/migrations/0004_query_stock.py
query_inspector/migrations/0005_alter_query_options.py
query_inspector/migrations/0006_query_from_materialized_view_query_from_view.py
query_inspector/migrations/0007_query_enabled_alter_query_slug.py
query_inspector/migrations/__init__.py
query_inspector/migrations/__pycache__/0001_initial.cpython-310.pyc
query_inspector/migrations/__pycache__/0001_initial.cpython-312.pyc
query_inspector/migrations/__pycache__/0001_initial.cpython-38.pyc
query_inspector/migrations/__pycache__/0002_query_default_parameters.cpython-310.pyc
django_query_inspector-1.3.0.dist-info/LICENSE
django_query_inspector-1.3.0.dist-info/METADATA
django_query_inspector-1.3.0.dist-info/WHEEL
django_query_inspector-1.3.0.dist-info/top_level.txt
django_query_inspector-1.3.0.dist-info/RECORD
