Metadata-Version: 2.1
Name: django-query-inspector
Version: 1.3.0
Summary: A collection of tools to render, export and inspect Django Querysets.
Home-page: https://github.com/morlandi/django-query-inspector
Author: Mario Orlandi
Author-email: morlandi@brainstorm.it
License: MIT
Platform: UNKNOWN
Classifier: Framework :: Django
Classifier: Development Status :: 5 - Production/Stable
Classifier: Intended Audience :: Developers
Classifier: License :: OSI Approved :: MIT License
Classifier: Operating System :: OS Independent
Classifier: Programming Language :: Python
Classifier: Programming Language :: Python :: 3
Classifier: Framework :: Django
Classifier: Framework :: Django :: 3.0
